pytapo/__init__.py
pytapo/const.py
pytapo/version.py
pytapo/media_stream/__init__.py
pytapo/media_stream/_utils.py
pytapo/media_stream/convert.py
pytapo/media_stream/crypto.py
pytapo/media_stream/downloader.py
pytapo/media_stream/downloaderv2.py
pytapo/media_stream/error.py
pytapo/media_stream/pes.py
pytapo/media_stream/response.py
pytapo/media_stream/session.py
pytapo/media_stream/streamer.py
pytapo/media_stream/tsReader.py
pytapo-3.4.4.dist-info/LICENSE
pytapo-3.4.4.dist-info/METADATA
pytapo-3.4.4.dist-info/WHEEL
pytapo-3.4.4.dist-info/top_level.txt
pytapo-3.4.4.dist-info/RECORD
