Metadata-Version: 2.1
Name: pytapo
Version: 3.4.4
Summary: Python library for communication with Tapo Cameras
Home-page: https://github.com/JurajNyiri/pytapo
Author: Juraj Nyíri
Author-email: juraj.nyiri@gmail.com
License: MIT
Classifier: Programming Language :: Python :: 3
Classifier: License :: OSI Approved :: MIT License
Classifier: Operating System :: OS Independent
License-File: LICENSE
Requires-Dist: requests
Requires-Dist: urllib3
Requires-Dist: pycryptodome
Requires-Dist: rtp
Requires-Dist: python-kasa
